{
  "key_number": "4899229",
  "application_type": "WO(B)",
  "application_ref": "6038552",
  "date": "2015-04-19",
  "debtor_name": {
    "forenames": [
      "Taya",
      "Carol"
    ],
    "surname": "Fadel"
  },
  "debtor_alternative_name": [

  ],
  "gender": "N/A",
  "occupation": "Tailor",
  "residence": [
    {
      "address_lines": [
        "9055 Graham Passage",
        "Hegmannmouth",
        "Merseyside"
      ],
      "postcode": "YV85 8NH"
    }
  ],
  "residence_withheld": false,
  "business_address": {
    "address_lines": [
      "42685 Bogisich Branch",
      "Berenicefort",
      "Genesisfurt",
      "Durham"
    ],
    "postcode": "RP24 6MB"
  },
  "date_of_birth": "1969-05-31",
  "investment_property": [

  ]
}